WifiOrca/__init__.py
WifiOrca/main.py
WifiOrca/packet_fox_client.py
WifiOrca/packet_fox_server.py
WifiOrca-0.0.24.dist-info/METADATA
WifiOrca-0.0.24.dist-info/WHEEL
WifiOrca-0.0.24.dist-info/top_level.txt
WifiOrca-0.0.24.dist-info/RECORD
